setup.py
mylib_donghao/__init__.py
mylib_donghao/basic_function.py
mylib_donghao/buy.py
mylib_donghao/myDimReduce.py
mylib_donghao/myLinearProgramming.py
mylib_donghao/myMatrix.py
mylib_donghao/myNN.py
mylib_donghao/myPath.py
mylib_donghao/myPerceptron.py
mylib_donghao/myQueue.py
mylib_donghao/myRBM.py
mylib_donghao/mySVM.py
mylib_donghao/mySort.py
mylib_donghao/test.py
mylib_donghao.egg-info/PKG-INFO
mylib_donghao.egg-info/SOURCES.txt
mylib_donghao.egg-info/dependency_links.txt
mylib_donghao.egg-info/requires.txt
mylib_donghao.egg-info/top_level.txt