Metadata-Version: 2.1
Name: mylib-donghao
Version: 0.2.2
Summary: A pythono package by DONG HAO about machine learing and other math problems, which is just in test.
Home-page: https://github.com/
Author: Hao Dong
Author-email: 1440027762@qq.com
License: MIT License
Keywords: mylib_donghao
Platform: any
